redial/__init__.py
redial/__main__.py
redial/config.py
redial/hostinfo.py
redial/redial.py
redial/uistate.py
redial/utils.py
redial/xdg.py
redial/tree/node.py
redial/ui/dialog.py
redial/ui/footer.py
redial/ui/palette.py
redial/ui/tree.py
redial-0.9.dist-info/LICENSE
redial-0.9.dist-info/METADATA
redial-0.9.dist-info/WHEEL
redial-0.9.dist-info/entry_points.txt
redial-0.9.dist-info/top_level.txt
redial-0.9.dist-info/RECORD
