Metadata-Version: 2.1
Name: redial
Version: 0.9
Summary: SSH Connection Manager
Home-page: https://github.com/taypo/redial
Author: Bahadır Yağan
Author-email: bahadir.yagan@gmail.com
License: gpl3
Platform: any
Classifier: Development Status :: 4 - Beta
Classifier: Programming Language :: Python :: 3
Classifier: Operating System :: POSIX :: Linux
Classifier: Operating System :: MacOS :: MacOS X
Requires-Dist: urwid (==2.1.2)
Provides-Extra: testing
Requires-Dist: pytest ; extra == 'testing'
Requires-Dist: pytest-cov ; extra == 'testing'
